SACMES_PYTHON_PACKAGE/Config.py
SACMES_PYTHON_PACKAGE/GUI.py
SACMES_PYTHON_PACKAGE/GUI_CA.py
SACMES_PYTHON_PACKAGE/SACMES.py
SACMES_PYTHON_PACKAGE/__init__.py
SACMES_PYTHON_PACKAGE/helper.py
SACMES_PYTHON_PACKAGE-0.7.dist-info/LICENSE
SACMES_PYTHON_PACKAGE-0.7.dist-info/METADATA
SACMES_PYTHON_PACKAGE-0.7.dist-info/WHEEL
SACMES_PYTHON_PACKAGE-0.7.dist-info/top_level.txt
SACMES_PYTHON_PACKAGE-0.7.dist-info/RECORD
