Metadata-Version: 2.1
Name: SACMES_PYTHON_PACKAGE
Version: 0.7
Summary: Description of my package
Home-page: https://github.com/Mattywonger/SACMES_Python_Package
Author: Matthew Wong
Author-email: twong50@email.com
Classifier: Programming Language :: Python :: 3
Classifier: License :: OSI Approved :: MIT License
Classifier: Operating System :: OS Independent
License-File: LICENSE
